logger/__init__.py
logger/logger.py
neointerface/__init__.py
neointerface/neointerface.py
neointerface-4.1.2.dist-info/LICENSE
neointerface-4.1.2.dist-info/METADATA
neointerface-4.1.2.dist-info/WHEEL
neointerface-4.1.2.dist-info/top_level.txt
neointerface-4.1.2.dist-info/RECORD
