Metadata-Version: 2.1
Name: neointerface
Version: 4.1.2
Summary: A Python interface to use the Neo4j graph database
Home-page: UNKNOWN
Author: Alexey Kuznetsov, Julian West, Ben Grinsted, William McDermott
License: 
Requires-Dist: attrs ==22.1.0
Requires-Dist: certifi ==2022.9.24
Requires-Dist: chardet ==4.0.0
Requires-Dist: decorator ==4.4.2
Requires-Dist: idna ==2.10
Requires-Dist: iniconfig ==1.1.1
Requires-Dist: neo4j ==5.10.0
Requires-Dist: networkx ==2.5.1
Requires-Dist: numpy ==1.19.5
Requires-Dist: packaging ==21.3
Requires-Dist: pandas ==1.1.5
Requires-Dist: pluggy ==0.13.1
Requires-Dist: py ==1.11.0
Requires-Dist: pytest ==6.2.4
Requires-Dist: pytest-unordered ==0.4.1
Requires-Dist: python-dateutil ==2.8.2
Requires-Dist: pytz ==2022.6
Requires-Dist: requests ==2.25.1
Requires-Dist: six ==1.16.0
Requires-Dist: toml ==0.10.2
Requires-Dist: urllib3 ==1.26.12
